xyz_wechat/__init__.py
xyz_wechat/admin.py
xyz_wechat/apis.py
xyz_wechat/apps.py
xyz_wechat/choices.py
xyz_wechat/helper.py
xyz_wechat/models.py
xyz_wechat/receivers.py
xyz_wechat/serializers.py
xyz_wechat/signals.py
xyz_wechat/urls.py
xyz_wechat/migrations/0001_initial.py
xyz_wechat/migrations/0002_auto_20210329_2348.py
xyz_wechat/migrations/0003_auto_20210727_1829.py
xyz_wechat/migrations/__init__.py
xyz_wechat/mp/__init__.py
xyz_wechat/mp/auth_backends.py
xyz_wechat/mp/context_processors.py
xyz_wechat/mp/decorators.py
xyz_wechat/mp/forms.py
xyz_wechat/mp/helper.py
xyz_wechat/mp/signals.py
xyz_wechat/mp/urls.py
xyz_wechat/mp/views.py
xyz_wechat/templates/wechat/mp/qrlogin.html
xyz_wechat-0.3.0.dist-info/METADATA
xyz_wechat-0.3.0.dist-info/WHEEL
xyz_wechat-0.3.0.dist-info/top_level.txt
xyz_wechat-0.3.0.dist-info/RECORD
